[{},{"id":1,"username":"bablu","email":"anirudh.krishan@gmail.com","password":"123"},{"id":2,"name":"bablu","email":"anirudh.krishan@gmail.com","password":"12345"},{"id":3,"name":"bablu","email":"bablu123@gmail.com","password":"123"},{"id":4,"name":"amit","email":"amit@gmail.com","password":"123"},{"id":5,"name":"kunal","email":"kunal123@gmail.com","paasword":"kunal123"},{"id":6,"name":"aa","email":"aa@gmail.com","password":"123"},{"id":7,"name":"asd","email":"asd@fgmail.com","password":"123"},{"id":8,"name":"fbdc","email":"bablusaini@cloveritservices.com","password":"jhfvg"},{"id":9,"name":"","email":"","password":""},{"id":10,"name":"","email":"","password":""},{"id":11,"user":"&lt;div id='div-id'>name&lt;/div>","pass":"bablu@1234","mail":"abablu@gmail.com"},{"id":12,"user":"&lt;div id='div-id'>name&lt;/div>","pass":"bablu@1234","mail":"abablu@gmail.com"},{"id":13,"user":"hhhhhhh","pass":"bablu@1234","mail":"abablu@gmail.com"},{"id":14,"user":"hhhhhhh","pass":"bablu@1234","mail":"abablu@gmail.com"},{"id":15,"user":"hhhhhhh","pass":"bablu@1234","mail":"abablu@gmail.com"},{"id":16,"name":"","email":"","password":""}]